onlyfakes/__init__.py
onlyfakes/consts.py
onlyfakes/core.py
onlyfakes-1.dist-info/LICENSE
onlyfakes-1.dist-info/METADATA
onlyfakes-1.dist-info/WHEEL
onlyfakes-1.dist-info/top_level.txt
onlyfakes-1.dist-info/RECORD
